zalo_tts/__init__.py
zalo_tts/zalo_tts.py
ZaloTTS-0.0.3.dist-info/METADATA
ZaloTTS-0.0.3.dist-info/WHEEL
ZaloTTS-0.0.3.dist-info/top_level.txt
ZaloTTS-0.0.3.dist-info/RECORD
